ofglib/__init__.py
ofglib/prediction/__init__.py
ofglib/prediction/columns.py
ofglib/prediction/important_features.py
ofglib/prediction/model.py
ofglib/prediction/preprocessing.py
ofglib/utils/__init__.py
ofglib/utils/db.py
ofglib/utils/s3.py
ofglib-0.1.7.dist-info/LICENSE
ofglib-0.1.7.dist-info/METADATA
ofglib-0.1.7.dist-info/WHEEL
ofglib-0.1.7.dist-info/top_level.txt
ofglib-0.1.7.dist-info/RECORD
